idquant/Data_Processor.py
idquant/IDQ_notebook_control.py
idquant/Polynomial_Calculator.py
idquant/__init__.py
idquant-1.0.1.dist-info/LICENSE.txt
idquant-1.0.1.dist-info/METADATA
idquant-1.0.1.dist-info/WHEEL
idquant-1.0.1.dist-info/top_level.txt
idquant-1.0.1.dist-info/RECORD
